decasify-0.11.1.dist-info/METADATA
decasify-0.11.1.dist-info/WHEEL
decasify/__init__.py
decasify/decasify.cpython-313-x86_64-linux-gnu.so
decasify-0.11.1.dist-info/RECORD
