Metadata-Version: 2.4
Name: decasify
Version: 0.11.1
Classifier: Development Status :: 5 - Production/Stable
Classifier: Intended Audience :: Developers
Classifier: Natural Language :: English
Classifier: Natural Language :: Turkish
Classifier: Programming Language :: Python :: Implementation :: CPython
Classifier: Programming Language :: Python :: Implementation :: PyPy
Classifier: Programming Language :: Rust
Classifier: Topic :: Text Processing :: Filters
Requires-Dist: cffi
Home-Page: https://github.com/alerque/decasify
Requires-Python: >=3.8
